shotman/__init__.py
shotman/__main__.py
shotman/copy.svg
shotman/trash-alt.svg
shotman/version.py
shotman-0.1.3.dist-info/LICENCE
shotman-0.1.3.dist-info/LICENCE.font-awesome
shotman-0.1.3.dist-info/METADATA
shotman-0.1.3.dist-info/WHEEL
shotman-0.1.3.dist-info/entry_points.txt
shotman-0.1.3.dist-info/top_level.txt
shotman-0.1.3.dist-info/RECORD
