Metadata-Version: 2.1
Name: shotman
Version: 0.1.3
Summary: Simple, light, modern tool for screenshooting.
Home-page: https://gitlab.com/whynothugo/shotman
Author: Hugo Osvaldo Barrera
Author-email: hugo@barrera.io
License: ISC
Platform: UNKNOWN
Classifier: Development Status :: 5 - Production/Stable
Classifier: License :: OSI Approved :: ISC License (ISCL)
Classifier: Operating System :: POSIX
Classifier: Programming Language :: Python :: 3.9
Classifier: Topic :: Desktop Environment
Classifier: Topic :: Utilities
Requires-Dist: pyside6
